odoo/addons/web_editor_media_dialog_dms/README.rst
odoo/addons/web_editor_media_dialog_dms/__init__.py
odoo/addons/web_editor_media_dialog_dms/__manifest__.py
odoo/addons/web_editor_media_dialog_dms/i18n/es.po
odoo/addons/web_editor_media_dialog_dms/i18n/it.po
odoo/addons/web_editor_media_dialog_dms/i18n/sv.po
odoo/addons/web_editor_media_dialog_dms/i18n/web_editor_media_dialog_dms.pot
odoo/addons/web_editor_media_dialog_dms/models/__init__.py
odoo/addons/web_editor_media_dialog_dms/models/dms_file.py
odoo/addons/web_editor_media_dialog_dms/models/ir_binary.py
odoo/addons/web_editor_media_dialog_dms/readme/CONTRIBUTORS.md
odoo/addons/web_editor_media_dialog_dms/readme/DESCRIPTION.md
odoo/addons/web_editor_media_dialog_dms/readme/USAGE.md
odoo/addons/web_editor_media_dialog_dms/static/description/icon.png
odoo/addons/web_editor_media_dialog_dms/static/description/index.html
odoo/addons/web_editor_media_dialog_dms/static/src/media_dialog/dms_selector.esm.js
odoo/addons/web_editor_media_dialog_dms/static/src/media_dialog/dms_selector.xml
odoo/addons/web_editor_media_dialog_dms/static/src/media_dialog/media_dialog.esm.js
odoo_addon_web_editor_media_dialog_dms-18.0.1.0.1.2.dist-info/METADATA
odoo_addon_web_editor_media_dialog_dms-18.0.1.0.1.2.dist-info/WHEEL
odoo_addon_web_editor_media_dialog_dms-18.0.1.0.1.2.dist-info/top_level.txt
odoo_addon_web_editor_media_dialog_dms-18.0.1.0.1.2.dist-info/RECORD
